halo/__init__.py
halo/auth.py
halo/client.py
halo/exceptions.py
halo/session.py
halo/resources/__init__.py
halo/resources/actions.py
halo/resources/assets.py
halo/resources/attachments.py
halo/resources/base.py
halo/resources/categories.py
halo/resources/clients.py
halo/resources/comments.py
halo/resources/fields.py
halo/resources/kb_articles.py
halo/resources/reports.py
halo/resources/ticket_types.py
halo/resources/tickets.py
halo/resources/users.py
haloitsm_python-0.1.0.dist-info/licenses/LICENSE
haloitsm_python-0.1.0.dist-info/METADATA
haloitsm_python-0.1.0.dist-info/WHEEL
haloitsm_python-0.1.0.dist-info/top_level.txt
haloitsm_python-0.1.0.dist-info/RECORD
