Metadata-Version: 2.4
Name: haloitsm-python
Version: 0.1.0
Summary: A clean Python client for the Halo ITSM REST API
Author-email: Chris Bland <cbland@bdq.cloud>
Maintainer-email: Chris Bland <cbland@bdq.cloud>
License: MIT
Project-URL: Homepage, https://github.com/yourusername/haloitsm-python
Project-URL: Documentation, https://github.com/yourusername/haloitsm-python#readme
Project-URL: Repository, https://github.com/yourusername/haloitsm-python.git
Project-URL: Bug Reports, https://github.com/yourusername/haloitsm-python/issues
Project-URL: Changelog, https://github.com/yourusername/haloitsm-python/blob/main/CHANGELOG.md
Keywords: halo,itsm,api,client,service desk,ticketing
Classifier: Development Status :: 3 - Alpha
Classifier: Intended Audience :: Developers
Classifier: Topic :: Software Development :: Libraries :: Python Modules
Classifier: License :: OSI Approved :: MIT License
Classifier: Programming Language :: Python :: 3
Classifier: Programming Language :: Python :: 3.8
Classifier: Programming Language :: Python :: 3.9
Classifier: Programming Language :: Python :: 3.10
Classifier: Programming Language :: Python :: 3.11
Classifier: Programming Language :: Python :: 3.12
Classifier: Operating System :: OS Independent
Requires-Python: >=3.8
License-File: LICENSE
Requires-Dist: requests>=2.28.0
Requires-Dist: urllib3>=1.26.0
Provides-Extra: dev
Requires-Dist: pytest>=7.0.0; extra == "dev"
Requires-Dist: pytest-cov>=3.0.0; extra == "dev"
Requires-Dist: black>=22.0.0; extra == "dev"
Requires-Dist: flake8>=4.0.0; extra == "dev"
Requires-Dist: mypy>=0.950; extra == "dev"
Requires-Dist: requests-mock>=1.9.0; extra == "dev"
Dynamic: license-file
